title_setter/__init__.py
title_setter/project_title_setter.py
title_setter-0.1.0.dist-info/WHEEL
title_setter-0.1.0.dist-info/METADATA
title_setter-0.1.0.dist-info/RECORD
