Metadata-Version: 2.1
Name: title-setter
Version: 0.1.0
Summary: 
Author: azartoosa
Author-email: azartoosa@gmail.com
Requires-Python: >=3.7,<4.0
Classifier: Programming Language :: Python :: 3
Classifier: Programming Language :: Python :: 3.7
Classifier: Programming Language :: Python :: 3.8
Classifier: Programming Language :: Python :: 3.9
Requires-Dist: pathlib (>=1.0.1,<2.0.0)
